odoo/addons/web_widget_many2many_tags_multi_selection/README.rst
odoo/addons/web_widget_many2many_tags_multi_selection/__init__.py
odoo/addons/web_widget_many2many_tags_multi_selection/__manifest__.py
odoo/addons/web_widget_many2many_tags_multi_selection/i18n/lt.po
odoo/addons/web_widget_many2many_tags_multi_selection/i18n/nl_NL.po
odoo/addons/web_widget_many2many_tags_multi_selection/i18n/pt_BR.po
odoo/addons/web_widget_many2many_tags_multi_selection/i18n/web_widget_many2many_tags_multi_selection.pot
odoo/addons/web_widget_many2many_tags_multi_selection/static/description/icon.png
odoo/addons/web_widget_many2many_tags_multi_selection/static/src/js/view_form.js
odoo/addons/web_widget_many2many_tags_multi_selection/views/web_widget_many2many_tags_multi_selection.xml
odoo11_addon_web_widget_many2many_tags_multi_selection-11.0.1.0.2.dist-info/METADATA
odoo11_addon_web_widget_many2many_tags_multi_selection-11.0.1.0.2.dist-info/WHEEL
odoo11_addon_web_widget_many2many_tags_multi_selection-11.0.1.0.2.dist-info/top_level.txt
odoo11_addon_web_widget_many2many_tags_multi_selection-11.0.1.0.2.dist-info/RECORD
